LICENSE
MANIFEST.in
README.md
setup.py
htmllogger/Htmllogger.py
htmllogger/__init__.py
htmllogger.egg-info/PKG-INFO
htmllogger.egg-info/SOURCES.txt
htmllogger.egg-info/dependency_links.txt
htmllogger.egg-info/requires.txt
htmllogger.egg-info/top_level.txt
htmllogger/css/images/bug.png
htmllogger/css/images/collapse.png
htmllogger/css/images/collapse_old.png
htmllogger/css/images/expand.png
htmllogger/css/images/expand_2.png
htmllogger/css/images/expand_old.png
htmllogger/css/images/fail.png
htmllogger/css/images/fail_4.png
htmllogger/css/images/fail_4_old.png
htmllogger/css/images/fail_old.png
htmllogger/css/images/file.png
htmllogger/css/images/folder.png
htmllogger/css/images/logo.png
htmllogger/css/images/pass.png
htmllogger/css/images/pass_4.png
htmllogger/css/images/pass_4_old.png
tests/__init__.py
tests/htmllogger_unittest.py
tests/test_pytest.py