Metadata-Version: 2.1
Name: htmllogger
Version: 0.1
Summary: Python library provides interactive test report for selenium
Home-page: https://github.com/PrashantP9070/htmllogger
Author: Prashant Pawar
Author-email: prashantpawar7090@gmail.com
License: MIT
Keywords: selenium,page object model,pom,pages,page factory,htmllogger,html report
Platform: UNKNOWN
